setup.py
snd_probability/Binomialdistribution.py
snd_probability/Gaussiandistribution.py
snd_probability/Generaldistribution.py
snd_probability/__init__.py
snd_probability.egg-info/PKG-INFO
snd_probability.egg-info/SOURCES.txt
snd_probability.egg-info/dependency_links.txt
snd_probability.egg-info/not-zip-safe
snd_probability.egg-info/top_level.txt