Metadata-Version: 1.0
Name: snd-probability
Version: 0.1
Summary: Gaussian and Binomial distributions
Home-page: UNKNOWN
Author: Divyesh Mangroliya
Author-email: UNKNOWN
License: UNKNOWN
Platform: UNKNOWN
